android_env/__init__.py
android_env/env_interface.py
android_env/environment.py
android_env/environment_test.py
android_env/loader.py
android_env/loader_test.py
android_env/components/__init__.py
android_env/components/action_type.py
android_env/components/adb_call_parser.py
android_env/components/adb_call_parser_test.py
android_env/components/adb_controller.py
android_env/components/adb_controller_test.py
android_env/components/adb_log_stream.py
android_env/components/adb_log_stream_test.py
android_env/components/app_screen_checker.py
android_env/components/app_screen_checker_test.py
android_env/components/coordinator.py
android_env/components/coordinator_test.py
android_env/components/dumpsys_thread.py
android_env/components/dumpsys_thread_test.py
android_env/components/errors.py
android_env/components/errors_test.py
android_env/components/log_stream.py
android_env/components/log_stream_test.py
android_env/components/logcat_thread.py
android_env/components/logcat_thread_test.py
android_env/components/setup_step_interpreter.py
android_env/components/setup_step_interpreter_test.py
android_env/components/specs.py
android_env/components/specs_test.py
android_env/components/task_manager.py
android_env/components/task_manager_test.py
android_env/components/utils.py
android_env/components/utils_test.py
android_env/components/simulators/__init__.py
android_env/components/simulators/base_simulator.py
android_env/components/simulators/base_simulator_test.py
android_env/components/simulators/emulator/__init__.py
android_env/components/simulators/emulator/emulator_launcher.py
android_env/components/simulators/emulator/emulator_launcher_test.py
android_env/components/simulators/emulator/emulator_simulator.py
android_env/components/simulators/emulator/emulator_simulator_test.py
android_env/components/simulators/fake/__init__.py
android_env/components/simulators/fake/fake_simulator.py
android_env/components/simulators/fake/fake_simulator_test.py
android_env/proto/__init__.py
android_env-1.2.2.dist-info/LICENSE
android_env-1.2.2.dist-info/METADATA
android_env-1.2.2.dist-info/WHEEL
android_env-1.2.2.dist-info/top_level.txt
android_env-1.2.2.dist-info/RECORD
