Metadata-Version: 2.1
Name: android-env
Version: 1.2.2
Summary: AndroidEnv environment and library for training agents.
Home-page: https://github.com/deepmind/android_env
Author: DeepMind
License: 
Project-URL: repository, https://github.com/deepmind/android_env
Project-URL: deepmind, https://www.deepmind.com/publications/androidenv-the-android-learning-environment
Project-URL: arxiv, https://arxiv.org/abs/2105.13231
Keywords: Android,OS,reinforcement-learning
Requires-Python: >=3.10
License-File: LICENSE
Requires-Dist: absl-py (>=0.1.0)
Requires-Dist: dm-env
Requires-Dist: grpcio
Requires-Dist: numpy (>=1.21)
Requires-Dist: portpicker (>=1.2.0)
Requires-Dist: protobuf (>=2.6)
Requires-Dist: pygame
Provides-Extra: acme
Requires-Dist: dm-acme ; extra == 'acme'
Provides-Extra: gym
Requires-Dist: gym ; extra == 'gym'
Provides-Extra: testing
Requires-Dist: attrs (==20.3.0) ; extra == 'testing'
Requires-Dist: gym ; extra == 'testing'
Requires-Dist: pillow ; extra == 'testing'
Requires-Dist: pytype ; extra == 'testing'
Requires-Dist: pytest-xdist ; extra == 'testing'
